setup.py
manoutils/__init__.py
manoutils.egg-info/PKG-INFO
manoutils.egg-info/SOURCES.txt
manoutils.egg-info/dependency_links.txt
manoutils.egg-info/not-zip-safe
manoutils.egg-info/top_level.txt
manoutils/business/ExsysRequest.py
manoutils/business/InnerRequest.py
manoutils/business/PublicRequest.py
manoutils/business/RequestIdMiddleware.py
manoutils/business/RequestTracer.py
manoutils/business/ServiceFinder.py
manoutils/business/__init__.py
manoutils/client/CertClient.py
manoutils/client/EsClient.py
manoutils/client/ExsysClient.py
manoutils/client/RedisClient.py
manoutils/client/SftpClient.py
manoutils/client/TokenClient.py
manoutils/client/__init__.py
manoutils/client/exsys/HttpBackend.py
manoutils/client/exsys/RedisBackend.py
manoutils/client/exsys/__init__.py
manoutils/common/__init__.py
manoutils/common/common.py
manoutils/common/constant.py
manoutils/config/ConfigManager.py
manoutils/config/__init__.py
manoutils/config/defualtConfig.py
manoutils/lock/FileLock.py
manoutils/lock/__init__.py
manoutils/log/LogTemplate.py
manoutils/log/__init__.py
manoutils/operator/FileOperator.py
manoutils/operator/__init__.py
manoutils/test/__init__.py
manoutils/utils/__init__.py
manoutils/wrapper/__init__.py
manoutils/wrapper/wrapper.py