Metadata-Version: 1.0
Name: manoutils
Version: 0.1.0
Summary: utils for Mano
Home-page: UNKNOWN
Author: wangkaiyue
Author-email: UNKNOWN
License: UNKNOWN
Platform: UNKNOWN
